{
  "sections": {
    "main": {
      "type": "s_article",
      "blocks": {
        "featured_image": {
          "type": "featured_image",
          "settings": {}
        },
        "title": {
          "type": "title",
          "settings": {}
        },
        "content": {
          "type": "content",
          "settings": {}
        },
        "comments": {
          "type": "comments",
          "settings": {}
        }
      },
      "block_order": [
        "featured_image",
        "title",
        "content",
        "comments"
      ],
      "settings": {}
    }
  },
  "order": [
    "main"
  ]
}